modular_sdk/__init__.py
modular_sdk/modular.py
modular_sdk/commons/__init__.py
modular_sdk/commons/constants.py
modular_sdk/commons/exception.py
modular_sdk/commons/helpers.py
modular_sdk/commons/log_helper.py
modular_sdk/commons/time_helper.py
modular_sdk/commons/trace_helper.py
modular_sdk/connections/__init__.py
modular_sdk/connections/rabbit_connection.py
modular_sdk/models/__init__.py
modular_sdk/models/application.py
modular_sdk/models/base_meta.py
modular_sdk/models/customer.py
modular_sdk/models/customer_settings.py
modular_sdk/models/execution_trace.py
modular_sdk/models/heartbeat.py
modular_sdk/models/job.py
modular_sdk/models/operation_mode.py
modular_sdk/models/parent.py
modular_sdk/models/region.py
modular_sdk/models/setting.py
modular_sdk/models/tenant.py
modular_sdk/models/tenant_settings.py
modular_sdk/models/pynamongo/__init__.py
modular_sdk/models/pynamongo/adapter.py
modular_sdk/models/pynamongo/attributes.py
modular_sdk/models/pynamongo/convertors.py
modular_sdk/models/pynamongo/indexes_creator.py
modular_sdk/models/pynamongo/models.py
modular_sdk/models/pynamongo/patch.py
modular_sdk/services/__init__.py
modular_sdk/services/application_service.py
modular_sdk/services/aws_creds_provider.py
modular_sdk/services/customer_service.py
modular_sdk/services/customer_settings_service.py
modular_sdk/services/environment_service.py
modular_sdk/services/events_service.py
modular_sdk/services/job_service.py
modular_sdk/services/lambda_service.py
modular_sdk/services/parent_service.py
modular_sdk/services/rabbit_transport_service.py
modular_sdk/services/region_service.py
modular_sdk/services/settings_management_service.py
modular_sdk/services/sqs_service.py
modular_sdk/services/ssm_service.py
modular_sdk/services/sts_service.py
modular_sdk/services/tenant_service.py
modular_sdk/services/tenant_settings_service.py
modular_sdk/services/thread_local_storage_service.py
modular_sdk/services/impl/__init__.py
modular_sdk-7.1.8.dist-info/licenses/LICENSE
modular_sdk-7.1.8.dist-info/METADATA
modular_sdk-7.1.8.dist-info/WHEEL
modular_sdk-7.1.8.dist-info/top_level.txt
modular_sdk-7.1.8.dist-info/RECORD
