Metadata-Version: 2.4
Name: modular_sdk
Version: 7.1.8
Summary: Data level integration for services built atop of Modular Framework
Author-email: EPAM Systems <support@syndicate.team>
License:                                  Apache License
Project-URL: Homepage, https://github.com/epam/modular-sdk
Project-URL: Documentation, https://github.com/epam/modular-sdk/blob/main/README.md
Project-URL: Repository, https://github.com/me/spam.git
Project-URL: Changelog, https://github.com/epam/modular-sdk/blob/main/CHANGELOG.md
Classifier: Programming Language :: Python :: 3
Classifier: License :: OSI Approved :: Apache Software License
Classifier: Operating System :: OS Independent
Requires-Python: >=3.10
License-File: LICENSE
Requires-Dist: pika==1.3.2
Requires-Dist: boto3<2,>=1.36.11
Requires-Dist: botocore<2,>=1.36.11
Requires-Dist: pymongo~=4.11.2
Requires-Dist: python-dateutil>=2.9.0.post0
Requires-Dist: cachetools<=6.2.2,>=5.5.1
Requires-Dist: pynamodb==6.1.0
Provides-Extra: cryptography
Requires-Dist: cryptography~=43.0.3; extra == "cryptography"
Provides-Extra: hvac
Requires-Dist: hvac~=2.1.0; extra == "hvac"
Dynamic: license-file
